ffutils/__init__.py
ffutils/binaries.py
ffutils/download.py
ffutils/execute.py
ffutils-2025.3.11.dist-info/LICENSE
ffutils-2025.3.11.dist-info/METADATA
ffutils-2025.3.11.dist-info/WHEEL
ffutils-2025.3.11.dist-info/top_level.txt
ffutils-2025.3.11.dist-info/RECORD
