Metadata-Version: 2.2
Name: ffutils
Version: 2025.3.11
Summary: Utilities for working with ffmpeg
Home-page: https://github.com/dsymbol/ffutils
Author: dsymbol
License: OSI Approved :: MIT License
Classifier: Programming Language :: Python :: 3
Classifier: License :: OSI Approved :: MIT License
License-File: LICENSE
Requires-Dist: rich==13.9.4
Requires-Dist: platformdirs==4.3.6
Requires-Dist: requests
Dynamic: author
Dynamic: classifier
Dynamic: description
Dynamic: description-content-type
Dynamic: home-page
Dynamic: license
Dynamic: requires-dist
Dynamic: summary
